{
  "uuid": "91d581f1-f4e9-4a2a-9315-7fdac84227e0",
  "name": "СопоставлениеНоменклатуры_СБИС",
  "name2": {
    "ru": "Сопоставление номенклатура СБИС"
  },
  "comment": "",
  "h1_0": "0",
  "h0": "0",
  "h5": [],
  "data": [
    [
      "1",
      [
        "1",
        [
          "0",
          [
            "9",
            [
              "0",
              [
                "0",
                "0",
                "91d581f1-f4e9-4a2a-9315-7fdac84227e0"
              ],
              "\"СопоставлениеНоменклатуры_СБИС\"",
              [
                "1",
                "\"ru\"",
                "\"Сопоставление номенклатура СБИС\""
              ],
              "\"\""
            ],
            "0",
            "0"
          ],
          [
            "0"
          ]
        ]
      ],
      "0"
    ]
  ],
  "Включать в содержание справки": "0",
  "Тип формы": "0",
  "Версия803": "9",
  "Расширенное представление": [
    "0"
  ],
  "code_encoding_obj": "utf-8-sig",
  "code_info_obj": 1
}