{
  "uuid": "a92d3c04-6de9-407d-b28e-743e741606a3",
  "name": "ФормаОтправкиКорреспонденции",
  "name2": {
    "ru": "Форма отправки корреспонденции"
  },
  "comment": "",
  "h1_0": "0",
  "h0": "0",
  "h5": [],
  "data": [
    [
      "1",
      [
        "1",
        [
          "0",
          [
            "9",
            [
              "0",
              [
                "0",
                "0",
                "a92d3c04-6de9-407d-b28e-743e741606a3"
              ],
              "\"ФормаОтправкиКорреспонденции\"",
              [
                "1",
                "\"ru\"",
                "\"Форма отправки корреспонденции\""
              ],
              "\"\""
            ],
            "0",
            "0"
          ],
          [
            "0"
          ]
        ]
      ],
      "0"
    ]
  ],
  "Включать в содержание справки": "0",
  "Тип формы": "0",
  "Версия803": "9",
  "Расширенное представление": [
    "0"
  ],
  "code_encoding_obj": "utf-8-sig",
  "code_info_obj": 1
}