{
  "file_uuid": "263763f4-3618-4aba-8eb8-3d8c7b88a0ac",
  "uuid": "748136c9-b5e8-4ecd-94cd-0150c70ef0da",
  "name": "СБИС",
  "name2": {
    "ru": "Электронный обмен документами в СБиС"
  },
  "comment": "",
  "h1_0": "0",
  "h0": "0",
  "h5": [],
  "data": [
    [
      "1",
      [
        "263763f4-3618-4aba-8eb8-3d8c7b88a0ac"
      ],
      "1",
      [
        "c3831ec8-d8d5-4f93-8a22-f9bfae07327f",
        [
          "1",
          [
            "4",
            "e433c6c8-d6e6-4d73-8b48-ade1a6bd7dbd",
            "012e0205-c46a-4528-944b-18b04fbe547d",
            [
              "0",
              [
                "0",
                [
                  "0",
                  "0",
                  "748136c9-b5e8-4ecd-94cd-0150c70ef0da"
                ],
                "\"СБИС\"",
                [
                  "1",
                  "\"ru\"",
                  "\"Электронный обмен документами в СБиС\""
                ],
                "\"\""
              ]
            ],
            "19cadc2a-d840-492a-9e00-5103ff0c46e6",
            "\"\"",
            "00000000-0000-0000-0000-000000000000"
          ],
          "4",
          [
            "2bcef0d1-0981-11d6-b9b8-0050bae0a95d",
            "1",
            [
              [
                "0",
                [
                  "11",
                  "9bae6cb3-b909-428f-b008-92f16488f776",
                  "fb4a615e-7c2c-46ce-9b8d-131652ccb807",
                  "a060145b-0ec8-476f-96c7-2c29e8d84a5e",
                  "be0a3504-e697-4081-985a-edd206e2540e",
                  [
                    "0",
                    [
                      "0",
                      [
                        "0",
                        "0",
                        "a828158d-d921-4858-8ff7-0d003ae5bb28"
                      ],
                      "\"LongOperations\"",
                      [
                        "1",
                        "\"ru\"",
                        "\"Long operations\""
                      ],
                      "\"\""
                    ]
                  ],
                  "0",
                  [
                    "1",
                    [
                      "1",
                      "1",
                      [
                        "-3"
                      ],
                      "510405d3-2a0c-4fea-960a-7fee59b32f9b",
                      [
                        "8",
                        "24",
                        "1183c14f-f814-49c6-9233-a3c26b3f64cf",
                        [
                          "\"#\"",
                          "9ad557b1-249e-48dc-824b-3e149ecf10a6",
                          [
                            "3",
                            "0",
                            "0"
                          ]
                        ],
                        "2723eb98-b4c1-498a-a6f3-70444757902f",
                        [
                          "\"#\"",
                          "98ea8e5a-b586-442b-b944-6e3447734aa7",
                          "0"
                        ],
                        "2bbba66b-fabf-4863-8ba3-54b3c64c896e",
                        [
                          "\"B\"",
                          "0"
                        ],
                        "2c8143d5-4248-4c43-8bfb-307c0be2e415",
                        [
                          "\"B\"",
                          "0"
                        ],
                        "33c74a4d-561f-4bc0-9eaa-8d21c893c0a9",
                        [
                          "\"U\""
                        ],
                        "3eaf5a8b-06d6-47b0-ac7d-a9698247f499",
                        [
                          "\"U\""
                        ],
                        "4690ff70-e3fa-4914-9127-6a9acc5fc949",
                        [
                          "\"#\"",
                          "87024738-fc2a-4436-ada1-df79d395c424",
                          [
                            "0"
                          ]
                        ],
                        "4de03908-56f4-4396-a61e-17253afca9ac",
                        [
                          "\"B\"",
                          "0"
                        ],
                        "580c29e2-8af4-4258-882a-7cf8073e61c8",
                        [
                          "\"#\"",
                          "87024738-fc2a-4436-ada1-df79d395c424",
                          [
                            "0"
                          ]
                        ],
                        "6c4f7074-e7d4-48eb-b31b-132873666262",
                        [
                          "\"#\"",
                          "157fa490-4ce9-11d4-9415-008048da11f9",
                          [
                            "1",
                            "00000000-0000-0000-0000-000000000000"
                          ]
                        ],
                        "6e3a1131-37a3-4da5-8895-572d9d0c9db6",
                        [
                          "\"#\"",
                          "ace3fd07-11b2-477e-ab7f-36f0ea37c8dd",
                          [
                            "ace3fd07-11b2-477e-ab7f-36f0ea37c8dd",
                            "2"
                          ]
                        ],
                        "7ba608f2-e654-42a3-8885-334fe88ca910",
                        [
                          "\"U\""
                        ],
                        "88149a78-9448-4767-867b-0e650d165d2e",
                        [
                          "\"#\"",
                          "87024738-fc2a-4436-ada1-df79d395c424",
                          [
                            "0"
                          ]
                        ],
                        "90ae4b5d-e0fd-49ef-a008-d67c1e75038c",
                        [
                          "\"B\"",
                          "0"
                        ],
                        "9288a8ed-b259-46d0-a8e3-70d87956ff2d",
                        [
                          "\"U\""
                        ],
                        "b02800e9-a8d1-42ab-9a12-f673e92be968",
                        [
                          "\"B\"",
                          "0"
                        ],
                        "c65a541f-0b91-4f33-bc88-fbaaa57f9992",
                        [
                          "\"U\""
                        ],
                        "cf4abea3-37b2-11d4-940f-008048da11f9",
                        [
                          "\"#\"",
                          "87024738-fc2a-4436-ada1-df79d395c424",
                          [
                            "0"
                          ]
                        ],
                        "cf4abea4-37b2-11d4-940f-008048da11f9",
                        [
                          "\"S\"",
                          "\"\""
                        ],
                        "d4232326-022b-421e-b6d3-88e418f74327",
                        [
                          "\"#\"",
                          "3b8e6bdd-d648-49d5-af2f-d46d84f87dd5",
                          [
                            "3b8e6bdd-d648-49d5-af2f-d46d84f87dd5",
                            "1"
                          ]
                        ],
                        "e3da683b-c54a-457a-a243-b9b4f9bf76dd",
                        [
                          "\"#\"",
                          "b76a58b9-2a56-4e46-bb31-8e04ad9f31ae",
                          [
                            "5004",
                            "0"
                          ]
                        ],
                        "e6b3f5f3-bdf3-4ad0-bc60-7323b3feb208",
                        [
                          "\"U\""
                        ],
                        "f49e4ced-4033-4e6c-8755-9fbaaccd6078",
                        [
                          "\"S\"",
                          "\"\""
                        ],
                        "fcf503b8-1c06-454a-970c-06413e64aee5",
                        [
                          "\"#\"",
                          "f2eaae14-91a7-47b9-9d69-097877f41580",
                          [
                            "0",
                            "0"
                          ]
                        ]
                      ]
                    ]
                  ],
                  [
                    "0"
                  ]
                ]
              ],
              "1",
              [
                "5d24a9d1-098e-11d6-b9b8-0050bae0a95d",
                "11",
                [
                  [
                    "0",
                    [
                      "25",
                      [
                        "2",
                        [
                          "0",
                          [
                            "0",
                            "0",
                            "37cb747f-47bc-40a6-8925-b4b87e174aa5"
                          ],
                          "\"Id\"",
                          [
                            "1",
                            "\"ru\"",
                            "\"Id\""
                          ],
                          "\"\""
                        ],
                        [
                          "\"Pattern\"",
                          [
                            "\"S\"",
                            "80",
                            "1"
                          ]
                        ]
                      ],
                      "0",
                      [
                        "0"
                      ],
                      [
                        "0"
                      ],
                      "0",
                      "\"\"",
                      "0",
                      [
                        "\"U\""
                      ],
                      [
                        "\"U\""
                      ],
                      "0",
                      "00000000-0000-0000-0000-000000000000",
                      "2",
                      "0",
                      [
                        "5004",
                        "0"
                      ],
                      [
                        "3",
                        "0",
                        "0"
                      ],
                      [
                        "0",
                        "0"
                      ],
                      "0",
                      [
                        "0"
                      ],
                      [
                        "\"S\"",
                        "\"\""
                      ],
                      "0"
                    ]
                  ],
                  "0"
                ],
                [
                  [
                    "0",
                    [
                      "25",
                      [
                        "2",
                        [
                          "0",
                          [
                            "0",
                            "0",
                            "10fb51f8-b7a2-4bbe-8592-423ed679dfb3"
                          ],
                          "\"Operation\"",
                          [
                            "1",
                            "\"ru\"",
                            "\"Operation\""
                          ],
                          "\"\""
                        ],
                        [
                          "\"Pattern\"",
                          [
                            "\"S\"",
                            "99",
                            "1"
                          ]
                        ]
                      ],
                      "0",
                      [
                        "0"
                      ],
                      [
                        "0"
                      ],
                      "0",
                      "\"\"",
                      "0",
                      [
                        "\"U\""
                      ],
                      [
                        "\"U\""
                      ],
                      "0",
                      "00000000-0000-0000-0000-000000000000",
                      "2",
                      "0",
                      [
                        "5004",
                        "0"
                      ],
                      [
                        "3",
                        "0",
                        "0"
                      ],
                      [
                        "0",
                        "0"
                      ],
                      "0",
                      [
                        "0"
                      ],
                      [
                        "\"S\"",
                        "\"\""
                      ],
                      "0"
                    ]
                  ],
                  "0"
                ],
                [
                  [
                    "0",
                    [
                      "25",
                      [
                        "2",
                        [
                          "0",
                          [
                            "0",
                            "0",
                            "0220978f-771a-4897-9725-8af739ebe6d0"
                          ],
                          "\"Begin\"",
                          [
                            "1",
                            "\"ru\"",
                            "\"Begin\""
                          ],
                          "\"\""
                        ],
                        [
                          "\"Pattern\"",
                          [
                            "\"D\""
                          ]
                        ]
                      ],
                      "0",
                      [
                        "1",
                        "\"ru\"",
                        "\"ДФ='dd.MM.yyyy HH:mm:ss'\""
                      ],
                      [
                        "0"
                      ],
                      "0",
                      "\"\"",
                      "0",
                      [
                        "\"U\""
                      ],
                      [
                        "\"U\""
                      ],
                      "0",
                      "00000000-0000-0000-0000-000000000000",
                      "2",
                      "0",
                      [
                        "5004",
                        "0"
                      ],
                      [
                        "3",
                        "0",
                        "0"
                      ],
                      [
                        "0",
                        "0"
                      ],
                      "0",
                      [
                        "0"
                      ],
                      [
                        "\"U\""
                      ],
                      "0"
                    ]
                  ],
                  "0"
                ],
                [
                  [
                    "0",
                    [
                      "25",
                      [
                        "2",
                        [
                          "0",
                          [
                            "0",
                            "0",
                            "e957d67e-936f-4bef-a577-e1082728faa1"
                          ],
                          "\"Update\"",
                          [
                            "1",
                            "\"ru\"",
                            "\"Update\""
                          ],
                          "\"\""
                        ],
                        [
                          "\"Pattern\"",
                          [
                            "\"D\""
                          ]
                        ]
                      ],
                      "0",
                      [
                        "1",
                        "\"ru\"",
                        "\"ДФ='dd.MM.yyyy HH:mm:ss'\""
                      ],
                      [
                        "0"
                      ],
                      "0",
                      "\"\"",
                      "0",
                      [
                        "\"U\""
                      ],
                      [
                        "\"U\""
                      ],
                      "0",
                      "00000000-0000-0000-0000-000000000000",
                      "2",
                      "0",
                      [
                        "5004",
                        "0"
                      ],
                      [
                        "3",
                        "0",
                        "0"
                      ],
                      [
                        "0",
                        "0"
                      ],
                      "0",
                      [
                        "0"
                      ],
                      [
                        "\"U\""
                      ],
                      "0"
                    ]
                  ],
                  "0"
                ],
                [
                  [
                    "0",
                    [
                      "25",
                      [
                        "2",
                        [
                          "0",
                          [
                            "0",
                            "0",
                            "7185aef6-dc51-4fb1-934c-dc1a2ffc41ea"
                          ],
                          "\"State\"",
                          [
                            "1",
                            "\"ru\"",
                            "\"State\""
                          ],
                          "\"\""
                        ],
                        [
                          "\"Pattern\"",
                          [
                            "\"S\"",
                            "99",
                            "1"
                          ]
                        ]
                      ],
                      "0",
                      [
                        "0"
                      ],
                      [
                        "0"
                      ],
                      "0",
                      "\"\"",
                      "0",
                      [
                        "\"U\""
                      ],
                      [
                        "\"U\""
                      ],
                      "0",
                      "00000000-0000-0000-0000-000000000000",
                      "2",
                      "0",
                      [
                        "5004",
                        "0"
                      ],
                      [
                        "3",
                        "0",
                        "0"
                      ],
                      [
                        "0",
                        "0"
                      ],
                      "0",
                      [
                        "0"
                      ],
                      [
                        "\"S\"",
                        "\"\""
                      ],
                      "0"
                    ]
                  ],
                  "0"
                ],
                [
                  [
                    "0",
                    [
                      "25",
                      [
                        "2",
                        [
                          "0",
                          [
                            "0",
                            "0",
                            "1a865c79-b32c-49e1-a694-931cd373b73c"
                          ],
                          "\"Detail\"",
                          [
                            "1",
                            "\"ru\"",
                            "\"Detail\""
                          ],
                          "\"\""
                        ],
                        [
                          "\"Pattern\"",
                          [
                            "\"S\""
                          ]
                        ]
                      ],
                      "0",
                      [
                        "0"
                      ],
                      [
                        "0"
                      ],
                      "0",
                      "\"\"",
                      "0",
                      [
                        "\"U\""
                      ],
                      [
                        "\"U\""
                      ],
                      "0",
                      "00000000-0000-0000-0000-000000000000",
                      "2",
                      "0",
                      [
                        "5004",
                        "0"
                      ],
                      [
                        "3",
                        "0",
                        "0"
                      ],
                      [
                        "0",
                        "0"
                      ],
                      "0",
                      [
                        "0"
                      ],
                      [
                        "\"S\"",
                        "\"\""
                      ],
                      "0"
                    ]
                  ],
                  "0"
                ],
                [
                  [
                    "0",
                    [
                      "25",
                      [
                        "2",
                        [
                          "0",
                          [
                            "0",
                            "0",
                            "58f84277-42f8-48c1-8ee4-ba082eda0cc3"
                          ],
                          "\"SabyObjName\"",
                          [
                            "1",
                            "\"ru\"",
                            "\"Saby obj name\""
                          ],
                          "\"\""
                        ],
                        [
                          "\"Pattern\"",
                          [
                            "\"S\"",
                            "99",
                            "1"
                          ]
                        ]
                      ],
                      "0",
                      [
                        "0"
                      ],
                      [
                        "0"
                      ],
                      "0",
                      "\"\"",
                      "0",
                      [
                        "\"U\""
                      ],
                      [
                        "\"U\""
                      ],
                      "0",
                      "00000000-0000-0000-0000-000000000000",
                      "2",
                      "0",
                      [
                        "5004",
                        "0"
                      ],
                      [
                        "3",
                        "0",
                        "0"
                      ],
                      [
                        "0",
                        "0"
                      ],
                      "0",
                      [
                        "0"
                      ],
                      [
                        "\"S\"",
                        "\"\""
                      ],
                      "0"
                    ]
                  ],
                  "0"
                ],
                [
                  [
                    "0",
                    [
                      "25",
                      [
                        "2",
                        [
                          "0",
                          [
                            "0",
                            "0",
                            "bf5c1d0e-3578-4cb1-9b9f-5040532e931d"
                          ],
                          "\"SabyObjId\"",
                          [
                            "1",
                            "\"ru\"",
                            "\"Saby obj id\""
                          ],
                          "\"\""
                        ],
                        [
                          "\"Pattern\"",
                          [
                            "\"S\"",
                            "80",
                            "1"
                          ]
                        ]
                      ],
                      "0",
                      [
                        "0"
                      ],
                      [
                        "0"
                      ],
                      "0",
                      "\"\"",
                      "0",
                      [
                        "\"U\""
                      ],
                      [
                        "\"U\""
                      ],
                      "0",
                      "00000000-0000-0000-0000-000000000000",
                      "2",
                      "0",
                      [
                        "5004",
                        "0"
                      ],
                      [
                        "3",
                        "0",
                        "0"
                      ],
                      [
                        "0",
                        "0"
                      ],
                      "0",
                      [
                        "0"
                      ],
                      [
                        "\"S\"",
                        "\"\""
                      ],
                      "0"
                    ]
                  ],
                  "0"
                ],
                [
                  [
                    "0",
                    [
                      "25",
                      [
                        "2",
                        [
                          "0",
                          [
                            "0",
                            "0",
                            "99358139-3ce4-4afe-ba0d-f49537b1a039"
                          ],
                          "\"Progress\"",
                          [
                            "1",
                            "\"ru\"",
                            "\"Progress\""
                          ],
                          "\"\""
                        ],
                        [
                          "\"Pattern\"",
                          [
                            "\"N\"",
                            "3",
                            "0",
                            "1"
                          ]
                        ]
                      ],
                      "0",
                      [
                        "1",
                        "\"ru\"",
                        "\"ЧДЦ=0; ЧН=-; ЧФ=Ч%\""
                      ],
                      [
                        "0"
                      ],
                      "0",
                      "\"\"",
                      "0",
                      [
                        "\"U\""
                      ],
                      [
                        "\"S\"",
                        "\"100\""
                      ],
                      "0",
                      "00000000-0000-0000-0000-000000000000",
                      "2",
                      "0",
                      [
                        "5004",
                        "0"
                      ],
                      [
                        "3",
                        "0",
                        "0"
                      ],
                      [
                        "0",
                        "0"
                      ],
                      "0",
                      [
                        "1",
                        "\"ru\"",
                        "\"ЧДЦ=0; ЧФ=Ч%\""
                      ],
                      [
                        "\"U\""
                      ],
                      "0"
                    ]
                  ],
                  "0"
                ],
                [
                  [
                    "0",
                    [
                      "25",
                      [
                        "2",
                        [
                          "0",
                          [
                            "0",
                            "0",
                            "906fd866-458b-4096-b03a-c4def2ed7a23"
                          ],
                          "\"New\"",
                          [
                            "1",
                            "\"ru\"",
                            "\"New\""
                          ],
                          "\"\""
                        ],
                        [
                          "\"Pattern\"",
                          [
                            "\"B\""
                          ]
                        ]
                      ],
                      "0",
                      [
                        "0"
                      ],
                      [
                        "0"
                      ],
                      "0",
                      "\"\"",
                      "0",
                      [
                        "\"U\""
                      ],
                      [
                        "\"U\""
                      ],
                      "0",
                      "00000000-0000-0000-0000-000000000000",
                      "2",
                      "0",
                      [
                        "5004",
                        "0"
                      ],
                      [
                        "3",
                        "0",
                        "0"
                      ],
                      [
                        "0",
                        "0"
                      ],
                      "0",
                      [
                        "0"
                      ],
                      [
                        "\"U\""
                      ],
                      "0"
                    ]
                  ],
                  "0"
                ],
                [
                  [
                    "0",
                    [
                      "25",
                      [
                        "2",
                        [
                          "0",
                          [
                            "0",
                            "0",
                            "261185bb-2f1c-4acf-a6b0-896c0554c9a7"
                          ],
                          "\"StatePicture\"",
                          [
                            "1",
                            "\"ru\"",
                            "\"State picture\""
                          ],
                          "\"\""
                        ],
                        [
                          "\"Pattern\"",
                          [
                            "\"N\"",
                            "1",
                            "0",
                            "1"
                          ]
                        ]
                      ],
                      "0",
                      [
                        "0"
                      ],
                      [
                        "0"
                      ],
                      "0",
                      "\"\"",
                      "0",
                      [
                        "\"U\""
                      ],
                      [
                        "\"U\""
                      ],
                      "0",
                      "00000000-0000-0000-0000-000000000000",
                      "2",
                      "0",
                      [
                        "5004",
                        "0"
                      ],
                      [
                        "3",
                        "0",
                        "0"
                      ],
                      [
                        "0",
                        "0"
                      ],
                      "0",
                      [
                        "0"
                      ],
                      [
                        "\"U\""
                      ],
                      "0"
                    ]
                  ],
                  "0"
                ]
              ]
            ]
          ],
          [
            "3daea016-69b7-4ed4-9453-127911372fe6",
            "4",
            "be138a2d-1799-425c-a7c4-5ff8988e2078",
            "25b32bd5-5b43-45d7-a5b7-7e376fd5f9e6",
            "270f5144-5b0b-46de-80d3-a624394f1ffe",
            "b5bc486b-7a4d-42c4-8400-9f99b66aac13"
          ],
          [
            "d5b0e5ed-256d-401c-9c36-f630cafd8a62",
            "108",
            "a3088cff-4282-4798-835c-17e1a6256f27",
            "deeebb7c-173c-4554-bba6-11e780e50ffd",
            "19cadc2a-d840-492a-9e00-5103ff0c46e6",
            "203b0ebc-81de-40c3-806d-0fd1006d77aa",
            "ba9dcd3d-b7e2-43f9-84ce-892bf44b999f",
            "7d74b708-51a3-4fd9-b0ef-c6bab91e50bf",
            "492e1b68-f64c-4e9d-8f6d-aae6f8a0eb07",
            "1d272535-3d37-4478-9783-9a05001586cc",
            "666904cd-1393-47ee-bb74-e92933ba9953",
            "53a502bd-6a6b-4c5b-956e-003b8e801e2f",
            "d584a457-788f-4938-ac1e-2b45dd57ad64",
            "618ecf4d-d381-4a2a-9509-8bdc53a7fabc",
            "da6dd6b5-7757-4808-86ae-523b32dba072",
            "e9620264-aa26-4295-ac76-df202ebab150",
            "540c8a44-8bc1-4cd9-ae46-dfe0b3e36d2d",
            "589bbf35-9a04-4ba6-be7e-baded5ffaa95",
            "8738d1d1-41b2-4657-9c6c-26c137c47354",
            "a9af95db-a492-44fd-ab95-78f7579b4b70",
            "d1c6c933-eaab-4ff1-81d1-3b3326c53e73",
            "f11eca8b-1d55-4f58-a6bc-f6cf182aea54",
            "db1bf61f-f7fe-4fc3-afd4-9678aa480123",
            "737e8229-3a6d-4dea-8467-31d271d0c2e0",
            "190c6ebb-4768-4dda-99fe-e0c6af309754",
            "21b94ae9-e1ee-440d-ae9c-6426c480cf9d",
            "7c36120b-ef3f-4c32-adf1-79e2298ecb99",
            "ea561489-88cb-4af2-87df-244a1fcc03ad",
            "bea5b9bb-5d8a-48e1-8386-7c6209f8419a",
            "bf817365-eaf3-4ad3-b2dc-01e985a8a4f1",
            "3f9e1490-cb80-4a10-a41f-f0048da40932",
            "84a67252-360d-4fdc-a457-8d9245cc3d1e",
            "b25b832d-0af1-492d-b45d-03c81159b7ee",
            "a5a63904-4d91-44a0-b5f1-9b369b67cead",
            "d167a566-d94a-4c78-a836-07a955104a65",
            "d2cb7fc5-7589-4281-b64e-d3c8ee7b3c10",
            "d7b7bf73-a5c5-49a1-8419-a8af2ebc7091",
            "eb19fcb5-fb41-4c3f-9c0c-e4240ccbd429",
            "75f67c96-1345-48f7-a4c2-7a2090e07609",
            "08afc072-b250-4964-b4a1-9828fbdc49a6",
            "aa33592b-5766-44eb-9390-d0baaf638c65",
            "3719bc5b-e30c-4e7b-8be2-d318942c1bbb",
            "c25deef2-af63-45d3-9bea-2f9f35e41b2c",
            "3bf92c9e-3e25-46e6-8b12-3f71dbad87f2",
            "4c7b8b06-8c32-468b-a1cc-abcdfb1fa32d",
            "ab579501-fdb6-405b-badb-48dc7be0c691",
            "7ffbc900-1dd2-49a3-939a-03eec0531643",
            "4048c6c0-83ed-4fe8-8f3e-6d5d78da84ee",
            "096b0151-2b27-4143-8847-0301a2a27e29",
            "29579914-3e09-4caf-a79d-f2689a45ba98",
            "30ef424c-64b1-4ff3-a38f-2a5c7e737a99",
            "8765d17e-58d7-48d2-a8e4-45503212585f",
            "b6b1f390-0b3c-473f-80c0-00c23f328da6",
            "2d3a55b6-d053-4523-819d-ea571b2d4d87",
            "65eb84ef-72c0-4245-83fc-2e51591aab38",
            "2027368a-3c4e-40ee-8ffe-9b3a5ce1db1d",
            "74d94d71-15df-40c3-b517-b8f6c4f57b7e",
            "0873f05d-28b1-4daa-8c4e-1c3f4056fc5f",
            "0177ba17-3bbb-4af3-a4a8-1a977e1d3c79",
            "e30eef74-a893-493d-90bf-b17da904dddb",
            "f04f36a4-a159-4f48-864c-57dc9797de9e",
            "ea1c4c07-31c9-468c-81f3-9c97f73ac98c",
            "8d4ebf0d-6a1c-436c-b247-baaa3267598a",
            "fb6e2a98-61ea-4b78-a59c-ebaf1386f77f",
            "6a3c1d31-5f52-4c85-88ae-6dec477cfc01",
            "2c329012-d0b9-4f3f-9ff8-41de8c11f2b3",
            "51c2f540-5185-44c1-a590-4e49fe729098",
            "669157ff-6134-4936-ac9d-88d83514b1c9",
            "8e36319a-6c63-4eec-bd58-89903b38ee3a",
            "79b21676-4405-4bdc-872b-de0a4fb19299",
            "4a433b0b-dd07-4911-a525-2687445f0f28",
            "82ba52a9-0b89-4795-b289-9359dd8cef03",
            "ff25911c-a6ca-41ed-a737-fcabb08705c5",
            "27192c40-6ae1-4df3-9a36-e48169814d63",
            "05703b70-b486-43da-95b5-bfdf368a5a63",
            "bca91b71-7394-42e2-b046-9fcaa7d616e7",
            "7a55bc7a-bf1f-4806-9138-280381eef6a7",
            "23cbde5c-e70d-4194-bf64-53779d7bc447",
            "d8bfb94e-0681-4e36-a481-568ab7beb833",
            "836a2414-408b-4d59-a9c1-b7b4286bed7e",
            "196652b8-7a0a-4a21-8494-3f16578a5585",
            "95e674a4-4ac8-4969-afdb-fda0cde74ea4",
            "da9b6aa0-2526-4d6b-8b15-4c79a68f9d65",
            "f0c22522-4fd9-46e6-89d8-11e8624ade73",
            "b93b8a00-1d30-40cd-acb1-39b2e99b4533",
            "3120f6da-fa75-46eb-8369-ca95fa0c9119",
            "6e73ab11-6999-43d4-9f8a-2520528935e6",
            "d9611a41-f8e2-4a26-aea2-b4c3e1306f0f",
            "995b3d9c-4f55-4678-b3ec-fdf6ac7867a4",
            "4d861ebd-95a4-49aa-ab92-3c0a2575888b",
            "091fccda-1e5e-442b-9330-d031be9f4810",
            "30955796-38bc-421f-a539-3e8e85da0004",
            "04339751-f8c9-4b26-a6bf-1011e0ca0b38",
            "0d84ee31-955a-4c3d-991f-b22fcbb01bb5",
            "7eb088fc-6b63-4f70-949a-1b3c74e20069",
            "f9e0d3d9-9c44-4977-b960-ad60e0f24ab4",
            "9cbfef3a-dbb9-4464-b91f-d977e614376b",
            "d928f377-e0b7-47c1-bc87-a43f9e8b9e71",
            "f9d628ac-bd94-4618-9169-6afd23b2843c",
            "03a64623-6235-44c8-880c-e8c901bb226a",
            "41976078-ce56-4700-a668-d1bad91e8d02",
            "4b56dceb-1a14-4e0d-b55d-77ad106fe092",
            "c99b7794-99ec-41d7-840c-12aa440bcadc",
            "40c132a9-ca7f-455f-9f8e-6c77bde70248",
            "47cd6e47-ebe7-49b0-a9f9-6b8d5375cb22",
            "4846b42f-cf21-4d32-aaaa-143de81f63d1",
            "876f41c7-50e6-451a-9b0c-3e016a9bd568",
            "fb1c182e-0598-41fb-b454-6c36d516864a",
            "3394c3c7-4c9d-4bb5-ba00-7e3b92cce32a",
            "0cf127c6-0fc7-4098-aa79-62a709046253"
          ],
          [
            "ec6bb5e5-b7a8-4d75-bec9-658107a699cf",
            "2",
            [
              [
                "0",
                [
                  "25",
                  [
                    "2",
                    [
                      "0",
                      [
                        "0",
                        "0",
                        "dd061add-339d-4316-bbde-9c1083b7b742"
                      ],
                      "\"СсылкаНаОбъект\"",
                      [
                        "1",
                        "\"ru\"",
                        "\"Ссылка на объект\""
                      ],
                      "\"\""
                    ],
                    [
                      "\"Pattern\""
                    ]
                  ],
                  "0",
                  [
                    "0"
                  ],
                  [
                    "0"
                  ],
                  "0",
                  "\"\"",
                  "0",
                  [
                    "\"U\""
                  ],
                  [
                    "\"U\""
                  ],
                  "0",
                  "00000000-0000-0000-0000-000000000000",
                  "2",
                  "0",
                  [
                    "5004",
                    "0"
                  ],
                  [
                    "3",
                    "0",
                    "0"
                  ],
                  [
                    "0",
                    "0"
                  ],
                  "0",
                  [
                    "0"
                  ],
                  [
                    "\"S\"",
                    "\"\""
                  ],
                  "0"
                ]
              ],
              "0"
            ],
            [
              [
                "0",
                [
                  "25",
                  [
                    "2",
                    [
                      "0",
                      [
                        "0",
                        "0",
                        "847270fe-b74f-4065-abe4-3d9ea85cc060"
                      ],
                      "\"ДополнительныеПараметры\"",
                      [
                        "1",
                        "\"ru\"",
                        "\"Дополнительные параметры\""
                      ],
                      "\"\""
                    ],
                    [
                      "\"Pattern\""
                    ]
                  ],
                  "0",
                  [
                    "0"
                  ],
                  [
                    "0"
                  ],
                  "0",
                  "\"\"",
                  "0",
                  [
                    "\"U\""
                  ],
                  [
                    "\"U\""
                  ],
                  "0",
                  "00000000-0000-0000-0000-000000000000",
                  "2",
                  "0",
                  [
                    "5004",
                    "0"
                  ],
                  [
                    "3",
                    "0",
                    "0"
                  ],
                  [
                    "0",
                    "0"
                  ],
                  "0",
                  [
                    "0"
                  ],
                  [
                    "\"S\"",
                    "\"\""
                  ],
                  "0"
                ]
              ],
              "0"
            ]
          ]
        ]
      ]
    ]
  ],
  "v8unpack": "0.8.2",
  "versions": [
    [
      "1",
      "286",
      "\"bca91b71-7394-42e2-b046-9fcaa7d616e7\"",
      "96239c3d-df1b-4173-974e-cd832cb36d1d",
      "\"\"",
      "594376d1-04e9-43a0-b1a5-c7c13d74399b",
      "\"da6dd6b5-7757-4808-86ae-523b32dba072.1\"",
      "dd90acb1-e0ea-4bab-9678-195b3771b3a1",
      "\"da6dd6b5-7757-4808-86ae-523b32dba072.0\"",
      "ddd1d3ba-c2eb-4570-af86-23c4a4d77a25",
      "\"d2cb7fc5-7589-4281-b64e-d3c8ee7b3c10.0\"",
      "b5a3b979-ef86-4d4e-8735-218dcae22ed1",
      "\"79b21676-4405-4bdc-872b-de0a4fb19299.0\"",
      "eee29ac7-0d12-4324-bd5f-dfea16b32118",
      "\"ea561489-88cb-4af2-87df-244a1fcc03ad.0\"",
      "d158e6f6-6807-4bbc-b6b7-e18a9c14fd38",
      "\"2d3a55b6-d053-4523-819d-ea571b2d4d87\"",
      "402143f5-687f-4190-b4a3-a665eb3f5049",
      "\"a3088cff-4282-4798-835c-17e1a6256f27.0\"",
      "f283bea5-c59a-42e7-bab0-340e7885db21",
      "\"41976078-ce56-4700-a668-d1bad91e8d02\"",
      "9782919c-db0d-4d60-8324-17620fe85a1e",
      "\"c25deef2-af63-45d3-9bea-2f9f35e41b2c\"",
      "df749253-9a0f-48e0-81ee-e4491c63fb91",
      "\"7a55bc7a-bf1f-4806-9138-280381eef6a7\"",
      "e113df20-3a27-489a-9e7f-67aba58ad422",
      "\"da9b6aa0-2526-4d6b-8b15-4c79a68f9d65.1\"",
      "59dca9e3-4bab-43c0-b7e2-ca0f5e7ec952",
      "\"da9b6aa0-2526-4d6b-8b15-4c79a68f9d65.0\"",
      "7e2c6fb8-084a-48a7-8e4d-189d3cb1406d",
      "\"db1bf61f-f7fe-4fc3-afd4-9678aa480123.0\"",
      "49876891-db2c-4bc1-9060-cb399572980c",
      "\"05703b70-b486-43da-95b5-bfdf368a5a63.0\"",
      "a01b8117-00e2-40df-a71c-16d36343a56c",
      "\"4846b42f-cf21-4d32-aaaa-143de81f63d1\"",
      "51f69826-92fd-4da2-8627-6e8f5f04dbd3",
      "\"9cbfef3a-dbb9-4464-b91f-d977e614376b.0\"",
      "d47f8bd1-567b-45ec-a3ba-710f90855e46",
      "\"e30eef74-a893-493d-90bf-b17da904dddb.0\"",
      "a7573572-a24f-4bfd-b466-76e692d04fda",
      "\"30ef424c-64b1-4ff3-a38f-2a5c7e737a99.0\"",
      "10c4630d-a7a4-4954-9045-cec84ed6d497",
      "\"21214f60-2972-4657-ac4c-37862e64ff85\"",
      "4bf18da6-711f-4c00-9bc0-7b2f463a0bd2",
      "\"47cd6e47-ebe7-49b0-a9f9-6b8d5375cb22.0\"",
      "184da997-adfb-4022-94d4-61a4d9792663",
      "\"47cd6e47-ebe7-49b0-a9f9-6b8d5375cb22.1\"",
      "5b7d4882-2c9d-408f-a1ec-4ef5ea3f8853",
      "\"7112cb4b-0b47-4343-85ec-b4f3525500db\"",
      "8ad1915f-5cef-4ea6-9f03-cfe210922433",
      "\"4b56dceb-1a14-4e0d-b55d-77ad106fe092\"",
      "13abe972-d255-4dd9-bc8a-0cd5cdc6f1fb",
      "\"47cd6e47-ebe7-49b0-a9f9-6b8d5375cb22\"",
      "e96319f1-4536-4dec-84d7-0fc4657edc68",
      "\"091fccda-1e5e-442b-9330-d031be9f4810\"",
      "94ae6f33-5614-4584-8d21-719615e45a04",
      "\"e9620264-aa26-4295-ac76-df202ebab150.0\"",
      "81ec4776-8d58-4245-ac99-8dc2242adf15",
      "\"a3088cff-4282-4798-835c-17e1a6256f27\"",
      "2ffdd7e0-21dd-42e1-b940-22b576f36722",
      "\"fb1c182e-0598-41fb-b454-6c36d516864a\"",
      "5ca618d4-f3ac-4d94-bdb1-38de72fa3c0b",
      "\"fb1c182e-0598-41fb-b454-6c36d516864a.0\"",
      "83f31f4f-a788-4842-90a0-95f2375b459f",
      "\"27192c40-6ae1-4df3-9a36-e48169814d63\"",
      "4614f25d-3bf9-4517-b8cf-2449446b4793",
      "\"a5a63904-4d91-44a0-b5f1-9b369b67cead\"",
      "ebc4f57c-5f76-4fe0-9fe3-6e7ffc7e2fb9",
      "\"bca91b71-7394-42e2-b046-9fcaa7d616e7.0\"",
      "0b481c12-ea6a-4740-9eb5-7f158353e333",
      "\"bf817365-eaf3-4ad3-b2dc-01e985a8a4f1.0\"",
      "8ad4e69c-63d4-4511-875d-795a15d48548",
      "\"2c329012-d0b9-4f3f-9ff8-41de8c11f2b3\"",
      "f2319d7a-edf3-42a5-b025-6bb5aeef488a",
      "\"95e674a4-4ac8-4969-afdb-fda0cde74ea4.1\"",
      "f6ca9810-ee6a-4475-ba75-853baab2a211",
      "\"95e674a4-4ac8-4969-afdb-fda0cde74ea4.0\"",
      "51211e45-f557-4467-bd93-1ee7898f5307",
      "\"0177ba17-3bbb-4af3-a4a8-1a977e1d3c79\"",
      "130d4844-5c50-4ead-9913-dabc49d97a4b",
      "\"203b0ebc-81de-40c3-806d-0fd1006d77aa\"",
      "e3f1a83f-8207-4253-9271-1d271d0e2ac7",
      "\"b6b1f390-0b3c-473f-80c0-00c23f328da6.0\"",
      "3709c587-f127-49fc-bf9a-ccf762f872a4",
      "\"f0c22522-4fd9-46e6-89d8-11e8624ade73.0\"",
      "2ee6c3cf-0db8-4cc4-a182-843755e2b456",
      "\"f9d628ac-bd94-4618-9169-6afd23b2843c.1\"",
      "c7d19334-bca8-41c4-82fc-abc1b5bc201e",
      "\"f9d628ac-bd94-4618-9169-6afd23b2843c.0\"",
      "d4a56258-6081-4efd-b6b2-6682135b0222",
      "\"ea561489-88cb-4af2-87df-244a1fcc03ad\"",
      "8791e385-6f64-4cc9-8aff-376a67eedff6",
      "\"2c329012-d0b9-4f3f-9ff8-41de8c11f2b3.0\"",
      "b0dfffcf-a188-485c-a720-c46d0355e4a5",
      "\"748136c9-b5e8-4ecd-94cd-0150c70ef0da.0\"",
      "d9a9aac1-98a4-4418-9f80-904fbe2965cf",
      "\"3f9e1490-cb80-4a10-a41f-f0048da40932.0\"",
      "419a64c4-7f3b-45ee-b014-81add85f5837",
      "\"f0c22522-4fd9-46e6-89d8-11e8624ade73\"",
      "278491e4-3182-4b6b-9516-3bbfbd1569ef",
      "\"a9af95db-a492-44fd-ab95-78f7579b4b70.0\"",
      "007416bc-ed2e-4821-872c-05df9d3de622",
      "\"65eb84ef-72c0-4245-83fc-2e51591aab38.0\"",
      "6033df20-0755-494c-b298-fe8abfc8dd35",
      "\"f9d628ac-bd94-4618-9169-6afd23b2843c\"",
      "20f10276-7d25-4b63-955e-f7bb5f2461fc",
      "\"196652b8-7a0a-4a21-8494-3f16578a5585.0\"",
      "ae8f7242-d336-48c9-9259-c215479cda2d",
      "\"196652b8-7a0a-4a21-8494-3f16578a5585.1\"",
      "c22b29c1-5930-4217-8fe9-ba16d08692e1",
      "\"d1c6c933-eaab-4ff1-81d1-3b3326c53e73\"",
      "3fb02d15-3348-4c78-ac8e-64f8c39df1c7",
      "\"d928f377-e0b7-47c1-bc87-a43f9e8b9e71.0\"",
      "532154ee-cd9b-4120-b189-ae1376b38243",
      "\"ab579501-fdb6-405b-badb-48dc7be0c691\"",
      "42511a33-7fd8-4915-9a00-a0e22fa53360",
      "\"deeebb7c-173c-4554-bba6-11e780e50ffd\"",
      "ade4c977-a876-4652-a18e-3dfa4ddd3a16",
      "\"bea5b9bb-5d8a-48e1-8386-7c6209f8419a.0\"",
      "8fa60a8c-3585-4aa8-b5dc-b05e144d16de",
      "\"84a67252-360d-4fdc-a457-8d9245cc3d1e.0\"",
      "8d9d48d3-2924-4a6e-b4b9-8ddd858dc4bf",
      "\"4d861ebd-95a4-49aa-ab92-3c0a2575888b\"",
      "ee8a1d8b-def9-4a3f-8245-a3e06a83deb4",
      "\"7d74b708-51a3-4fd9-b0ef-c6bab91e50bf.1\"",
      "e65545e8-f555-4194-bb26-48772bd1e7f0",
      "\"7d74b708-51a3-4fd9-b0ef-c6bab91e50bf.0\"",
      "df6bd662-b302-4872-a018-02a32761399f",
      "\"323a9f05-d175-40e1-8e1d-fc968274fdf9\"",
      "5296018e-0afa-43f0-bc9a-15e3fa87bfdd",
      "\"1d272535-3d37-4478-9783-9a05001586cc.1\"",
      "6fd973bf-b6c9-45bd-aec8-bef130131703",
      "\"1d272535-3d37-4478-9783-9a05001586cc.0\"",
      "7ecdd13c-6d63-46dc-9cb7-28d665492528",
      "\"b6b1f390-0b3c-473f-80c0-00c23f328da6\"",
      "0faa1118-4439-44a9-807e-3eaf7f9d9ef0",
      "\"82ba52a9-0b89-4795-b289-9359dd8cef03.1\"",
      "fd4b25f9-de94-40c8-9c3b-3666791b091a",
      "\"82ba52a9-0b89-4795-b289-9359dd8cef03.0\"",
      "b4d85ff7-3c16-481a-94e4-c7770f4f99ab",
      "\"d7b7bf73-a5c5-49a1-8419-a8af2ebc7091\"",
      "bec5637c-cb9a-4e38-a122-571c9233bd98",
      "\"c99b7794-99ec-41d7-840c-12aa440bcadc\"",
      "69f1c768-3a38-41a6-9045-7674cece8828",
      "\"51c2f540-5185-44c1-a590-4e49fe729098\"",
      "e0ecd7f8-db99-49af-b970-f12d233d9c0c",
      "\"b25b832d-0af1-492d-b45d-03c81159b7ee\"",
      "32bb4fc4-b580-46c4-bc0d-401e5d63f27b",
      "\"3120f6da-fa75-46eb-8369-ca95fa0c9119\"",
      "02ae7743-3e2c-460e-bc19-9b72e271ecda",
      "\"79b21676-4405-4bdc-872b-de0a4fb19299\"",
      "c576be3e-54b4-4a50-a95b-9221a59faf1a",
      "\"74d94d71-15df-40c3-b517-b8f6c4f57b7e.0\"",
      "6a13a3a4-4a07-4f5a-99dc-05be5b982b7d",
      "\"74d94d71-15df-40c3-b517-b8f6c4f57b7e.1\"",
      "3aba4c81-5561-4978-95a5-0ebac7af8311",
      "\"0d84ee31-955a-4c3d-991f-b22fcbb01bb5.0\"",
      "47e525cf-50e1-46ad-bff7-09a741a92460",
      "\"82ba52a9-0b89-4795-b289-9359dd8cef03\"",
      "4cea1485-666f-4cf1-a637-5c8d46a13b1d",
      "\"7eb088fc-6b63-4f70-949a-1b3c74e20069\"",
      "f2ebe5d4-8b06-4915-aacd-7dabfd57b0af",
      "\"b5bc486b-7a4d-42c4-8400-9f99b66aac13.0\"",
      "ea9647a2-690a-44d8-8fd2-d77133fd8496",
      "\"d584a457-788f-4938-ac1e-2b45dd57ad64\"",
      "be4ad3e4-09d7-4ed3-b217-7df6de360707",
      "\"d2cb7fc5-7589-4281-b64e-d3c8ee7b3c10\"",
      "a976b853-0b71-4839-a50a-68710d10f448",
      "\"2027368a-3c4e-40ee-8ffe-9b3a5ce1db1d.0\"",
      "29fa91de-3f09-4405-85b4-a32943362718",
      "\"e9620264-aa26-4295-ac76-df202ebab150\"",
      "2c9f27dd-da3b-46cf-8700-1d550b28b313",
      "\"d928f377-e0b7-47c1-bc87-a43f9e8b9e71\"",
      "f9eea204-60b7-48d7-97f6-708f6c1c6a37",
      "\"737e8229-3a6d-4dea-8467-31d271d0c2e0.0\"",
      "4f1ec3ee-4138-4a59-a3e9-fd202028a733",
      "\"version\"",
      "68b1bee4-aa00-4fc8-994c-a7082999f29a",
      "\"ba9dcd3d-b7e2-43f9-84ce-892bf44b999f\"",
      "6c192626-0b8d-463f-b7a9-5fc1ded65e7a",
      "\"8d4ebf0d-6a1c-436c-b247-baaa3267598a.0\"",
      "75e48b25-1218-4eff-96dd-54b9a1a0c243",
      "\"8d4ebf0d-6a1c-436c-b247-baaa3267598a.1\"",
      "a38bea10-787e-49e4-ae60-8e57716f9046",
      "\"8738d1d1-41b2-4657-9c6c-26c137c47354.0\"",
      "d1c5066d-c940-48f4-8cda-f6b2d2fb5dd1",
      "\"d7b7bf73-a5c5-49a1-8419-a8af2ebc7091.0\"",
      "ec56c1f7-2dfb-4776-8dad-594548ef6bb2",
      "\"d1c6c933-eaab-4ff1-81d1-3b3326c53e73.0\"",
      "a22356a9-0f28-4114-ae04-56c3337a7b93",
      "\"fb6e2a98-61ea-4b78-a59c-ebaf1386f77f\"",
      "5b19b7de-37f9-4257-b715-e90d49bf1aa9",
      "\"41976078-ce56-4700-a668-d1bad91e8d02.1\"",
      "cec8dad9-5e8e-42ab-a66c-8a84e5787fa1",
      "\"41976078-ce56-4700-a668-d1bad91e8d02.0\"",
      "71f7e620-b271-44b6-aec9-8c339c97227f",
      "\"1d272535-3d37-4478-9783-9a05001586cc\"",
      "d758ea4e-bad3-44a5-8bda-6964c3232cc4",
      "\"8738d1d1-41b2-4657-9c6c-26c137c47354\"",
      "98ee3eb1-3263-40ee-a90f-e04440362b83",
      "\"40c132a9-ca7f-455f-9f8e-6c77bde70248.0\"",
      "786faf03-4a4b-4371-8f7c-d98fc5418a3e",
      "\"836a2414-408b-4d59-a9c1-b7b4286bed7e\"",
      "71ab52b5-a8f2-42e0-b8d9-72ec0ddc36ce",
      "\"b93b8a00-1d30-40cd-acb1-39b2e99b4533.0\"",
      "67496e5c-98ae-4d02-9429-51bd3f0db527",
      "\"03a64623-6235-44c8-880c-e8c901bb226a.0\"",
      "841f3454-2a3b-4baf-964b-61e0391572dc",
      "\"0d84ee31-955a-4c3d-991f-b22fcbb01bb5\"",
      "6d516246-4d84-4e5c-aeef-d2ac353f765b",
      "\"ba9dcd3d-b7e2-43f9-84ce-892bf44b999f.1\"",
      "d1e70f7b-6530-4bc5-8ed0-0daa2c1567ce",
      "\"ba9dcd3d-b7e2-43f9-84ce-892bf44b999f.0\"",
      "e619e980-d631-4901-8210-8d97f63de71e",
      "\"666904cd-1393-47ee-bb74-e92933ba9953\"",
      "d89a79f9-e2bc-4dbf-9171-8274b249fe52",
      "\"8e36319a-6c63-4eec-bd58-89903b38ee3a\"",
      "9539bd2f-aa35-4441-82e1-e7fa11ba6c43",
      "\"4d861ebd-95a4-49aa-ab92-3c0a2575888b.0\"",
      "4da2e039-2563-4b56-a3c2-590100ed17aa",
      "\"27192c40-6ae1-4df3-9a36-e48169814d63.0\"",
      "ab06ed67-4202-433c-a2cc-9d47e858b1ce",
      "\"540c8a44-8bc1-4cd9-ae46-dfe0b3e36d2d.0\"",
      "3c53822c-f03b-42c0-9496-73ace1eb8b5d",
      "\"d8bfb94e-0681-4e36-a481-568ab7beb833.0\"",
      "d9f0b27a-2756-4785-8a70-16b2b7c14447",
      "\"d8bfb94e-0681-4e36-a481-568ab7beb833.1\"",
      "7615673a-d6d1-4213-8e61-7d281b309373",
      "\"3394c3c7-4c9d-4bb5-ba00-7e3b92cce32a\"",
      "8e18ca56-3369-453c-8960-8612cc51b98e",
      "\"29579914-3e09-4caf-a79d-f2689a45ba98.0\"",
      "373cc4af-ca70-4622-9181-b0731cc19a33",
      "\"da6dd6b5-7757-4808-86ae-523b32dba072\"",
      "c44b1e3f-282e-48ce-a437-cc9b5730df16",
      "\"196652b8-7a0a-4a21-8494-3f16578a5585\"",
      "be644a85-f718-4b85-ab91-36b86c330f9a",
      "\"c99b7794-99ec-41d7-840c-12aa440bcadc.0\"",
      "2cf1319c-4d22-43fd-9d79-72de4f45f7f0",
      "\"c99b7794-99ec-41d7-840c-12aa440bcadc.1\"",
      "f12559bc-6289-4a73-8d56-1104d2bb6098",
      "\"ab579501-fdb6-405b-badb-48dc7be0c691.0\"",
      "723d074c-cfac-4bca-b48e-a7470ecaa294",
      "\"4a433b0b-dd07-4911-a525-2687445f0f28\"",
      "e7a31181-187e-4b3e-8dfc-fcb43515bf71",
      "\"589bbf35-9a04-4ba6-be7e-baded5ffaa95\"",
      "08c86c43-86f6-47d0-86b5-ba0f8bf86f25",
      "\"c25deef2-af63-45d3-9bea-2f9f35e41b2c.0\"",
      "c896dd0b-e0d7-4f98-9387-53ff837b9427",
      "\"c25deef2-af63-45d3-9bea-2f9f35e41b2c.1\"",
      "64c40e62-e155-4074-a943-d292b8d0204d",
      "\"7a55bc7a-bf1f-4806-9138-280381eef6a7.0\"",
      "5921003c-2956-4e02-9ac9-1a37748ea94a",
      "\"7a55bc7a-bf1f-4806-9138-280381eef6a7.1\"",
      "9bd78ea4-cfba-4d9c-b522-d52ade2b9876",
      "\"ea1c4c07-31c9-468c-81f3-9c97f73ac98c\"",
      "b1d120d3-954a-4316-b8c2-938e1f293bf9",
      "\"e30eef74-a893-493d-90bf-b17da904dddb\"",
      "b1fd4db9-b258-470f-b92f-1a9cd8ae5968",
      "\"8765d17e-58d7-48d2-a8e4-45503212585f.0\"",
      "83a76948-9cea-4fe5-9009-ec2061f2ff7a",
      "\"30ef424c-64b1-4ff3-a38f-2a5c7e737a99\"",
      "0902171c-6bc5-4145-8e78-5e008358d07b",
      "\"f9e0d3d9-9c44-4977-b960-ad60e0f24ab4.1\"",
      "290adc81-4251-4ea7-bdc4-b5f12abf2b8d",
      "\"f9e0d3d9-9c44-4977-b960-ad60e0f24ab4.0\"",
      "b0f8513d-267d-4b52-978d-b1b9c5675619",
      "\"4c7b8b06-8c32-468b-a1cc-abcdfb1fa32d.1\"",
      "d7ca8c61-ab06-4fb9-9039-36b6fb65cfc6",
      "\"4c7b8b06-8c32-468b-a1cc-abcdfb1fa32d.0\"",
      "86dbc737-882f-480b-975b-373c2c8d242f",
      "\"4048c6c0-83ed-4fe8-8f3e-6d5d78da84ee.0\"",
      "fd1bd962-d4e1-4547-93fa-5c7adbeb1a4d",
      "\"270f5144-5b0b-46de-80d3-a624394f1ffe.0\"",
      "d9fa0b61-343f-4e81-8d81-a12020aa7004",
      "\"492e1b68-f64c-4e9d-8f6d-aae6f8a0eb07\"",
      "a2451735-6ff4-4b82-b8af-87f01577515e",
      "\"a9af95db-a492-44fd-ab95-78f7579b4b70\"",
      "8864bf7c-ff58-47a6-b7eb-82d33d74eab7",
      "\"65eb84ef-72c0-4245-83fc-2e51591aab38\"",
      "e6fe4d5a-8e29-4230-8420-0a5de75b077c",
      "\"a5a63904-4d91-44a0-b5f1-9b369b67cead.0\"",
      "c7c5cba5-5f81-466b-af36-51f10b3e6bc2",
      "\"a5a63904-4d91-44a0-b5f1-9b369b67cead.1\"",
      "2f1e6c80-db1d-4a8f-b379-fad6ce909413",
      "\"19cadc2a-d840-492a-9e00-5103ff0c46e6.1\"",
      "2008240d-171d-43d3-bc1c-4c9e4a6822a5",
      "\"19cadc2a-d840-492a-9e00-5103ff0c46e6.0\"",
      "ba094a5c-f51b-43c9-be76-b930aa782f02",
      "\"9cbfef3a-dbb9-4464-b91f-d977e614376b\"",
      "ddff0ec8-7e85-4f5f-923f-f82399be676f",
      "\"6a3c1d31-5f52-4c85-88ae-6dec477cfc01.0\"",
      "5c51820d-e140-4be2-a8de-188c1926cbd2",
      "\"8d4ebf0d-6a1c-436c-b247-baaa3267598a\"",
      "b413bda2-9730-4976-bfb5-d6a5a7cc16e6",
      "\"3394c3c7-4c9d-4bb5-ba00-7e3b92cce32a.0\"",
      "19317159-478d-4c26-b4b6-edf384ee1a8b",
      "\"3394c3c7-4c9d-4bb5-ba00-7e3b92cce32a.1\"",
      "f7b79a20-9119-432b-97b1-4722bc09077d",
      "\"copyinfo\"",
      "e7974d01-f2b7-4b03-acb2-a967c580fcd8",
      "\"21b94ae9-e1ee-440d-ae9c-6426c480cf9d\"",
      "e33eeafd-085d-4f9c-bcc1-40cd0d6ebf75",
      "\"23cbde5c-e70d-4194-bf64-53779d7bc447\"",
      "47a9d498-9a85-4d5a-ab87-35c544532df8",
      "\"0177ba17-3bbb-4af3-a4a8-1a977e1d3c79.0\"",
      "9336a543-04f3-4376-bacf-2b62abc92bf8",
      "\"0177ba17-3bbb-4af3-a4a8-1a977e1d3c79.1\"",
      "bef722c7-75a8-4d23-ba4f-ae1da787189f",
      "\"091fccda-1e5e-442b-9330-d031be9f4810.1\"",
      "4d8526a8-f7b0-4f2e-8b99-26b23b4b0900",
      "\"091fccda-1e5e-442b-9330-d031be9f4810.0\"",
      "ad774cb8-c06d-49d4-bd10-5b40c1897f86",
      "\"618ecf4d-d381-4a2a-9509-8bdc53a7fabc.0\"",
      "a45cb710-e3b8-43c3-8144-60bf55207da6",
      "\"618ecf4d-d381-4a2a-9509-8bdc53a7fabc.1\"",
      "8dd1788b-8abf-459d-b8f9-9eff0302284e",
      "\"eb19fcb5-fb41-4c3f-9c0c-e4240ccbd429.0\"",
      "003fe574-5273-4fcf-9163-ecdff2718d76",
      "\"876f41c7-50e6-451a-9b0c-3e016a9bd568.1\"",
      "c326f7f9-5e73-4eef-b1c8-c9c73d708a44",
      "\"876f41c7-50e6-451a-9b0c-3e016a9bd568.0\"",
      "b810ecc1-e2ee-44ab-8603-b09ae657c2b5",
      "\"190c6ebb-4768-4dda-99fe-e0c6af309754.0\"",
      "81eecd3a-873f-4f0d-9d97-764f78ae4b14",
      "\"08afc072-b250-4964-b4a1-9828fbdc49a6\"",
      "24c13554-a290-4617-91bb-863893f42fa9",
      "\"d9611a41-f8e2-4a26-aea2-b4c3e1306f0f.0\"",
      "5384d597-419c-4384-8d4f-684f2a4f6c5d",
      "\"95e674a4-4ac8-4969-afdb-fda0cde74ea4\"",
      "54ed4b7a-472e-4843-b130-fde8405f3915",
      "\"4a433b0b-dd07-4911-a525-2687445f0f28.0\"",
      "e1c0b911-4841-4f9c-8d0e-313102b5a684",
      "\"29579914-3e09-4caf-a79d-f2689a45ba98\"",
      "911a98ad-d323-434b-9b97-7e8f3b710f09",
      "\"6a3c1d31-5f52-4c85-88ae-6dec477cfc01\"",
      "880ab80f-a289-4d87-bb88-f7988484b6e7",
      "\"995b3d9c-4f55-4678-b3ec-fdf6ac7867a4\"",
      "218890aa-c025-489e-befd-83aa5dd30c7c",
      "\"75f67c96-1345-48f7-a4c2-7a2090e07609\"",
      "bbbaa5cf-571c-46ee-8cb4-58d630fa362d",
      "\"0cf127c6-0fc7-4098-aa79-62a709046253\"",
      "9d968097-92df-44a2-853b-1e90338d21ca",
      "\"7c36120b-ef3f-4c32-adf1-79e2298ecb99\"",
      "81afd7f9-11a5-4338-b207-1f83585f04ed",
      "\"30955796-38bc-421f-a539-3e8e85da0004.0\"",
      "270d33df-32c9-4fbc-9ce3-d16aa1890a37",
      "\"74d94d71-15df-40c3-b517-b8f6c4f57b7e\"",
      "b06c47b0-d4f5-4492-83e5-bf3bac3a58fe",
      "\"270f5144-5b0b-46de-80d3-a624394f1ffe\"",
      "22b3fde1-9644-4986-ad3c-55fcf0e23896",
      "\"25b32bd5-5b43-45d7-a5b7-7e376fd5f9e6\"",
      "c51a29fc-f7b9-4a3c-9204-dd261bb4f4d4",
      "\"096b0151-2b27-4143-8847-0301a2a27e29\"",
      "2f94d389-370a-4e54-b820-5b83daf817c6",
      "\"04339751-f8c9-4b26-a6bf-1011e0ca0b38\"",
      "be1ae556-382c-40a3-b8b3-00e4d4049a90",
      "\"836a2414-408b-4d59-a9c1-b7b4286bed7e.0\"",
      "cc9c5e3f-3af6-4b4d-982a-d26c86ee7188",
      "\"836a2414-408b-4d59-a9c1-b7b4286bed7e.1\"",
      "e4d6cc7a-c11d-4d3d-90cf-ba702a6f4037",
      "\"737e8229-3a6d-4dea-8467-31d271d0c2e0\"",
      "a8f1e85f-c20d-4bfd-858d-ce1d55a53305",
      "\"7eb088fc-6b63-4f70-949a-1b3c74e20069.0\"",
      "be081115-8e41-41eb-82ba-df7ef5ae7694",
      "\"51c2f540-5185-44c1-a590-4e49fe729098.0\"",
      "19eaa9a6-099b-49d5-acb3-5fbebab61cb7",
      "\"51c2f540-5185-44c1-a590-4e49fe729098.1\"",
      "8f86edfa-5852-4ff5-ad2e-99f2d5801dae",
      "\"deeebb7c-173c-4554-bba6-11e780e50ffd.1\"",
      "239a47fe-f681-4a70-8f2d-1ac13f519d0a",
      "\"deeebb7c-173c-4554-bba6-11e780e50ffd.0\"",
      "1d9c3f4a-ec27-495c-aea0-34938ae8c05b",
      "\"4846b42f-cf21-4d32-aaaa-143de81f63d1.0\"",
      "e13460c4-1dd6-48bd-8ddf-c56c6dde684d",
      "\"4846b42f-cf21-4d32-aaaa-143de81f63d1.1\"",
      "fa9ae302-79a8-489b-b6f4-804134f21cbd",
      "\"669157ff-6134-4936-ac9d-88d83514b1c9.0\"",
      "b4882631-f4d0-4549-9f8b-dbb0ea5aa143",
      "\"versions\"",
      "fbb26714-999f-4f4f-a765-af36cafc2a80",
      "\"3bf92c9e-3e25-46e6-8b12-3f71dbad87f2.0\"",
      "94a1107a-c2c3-4eb9-bb87-456c59a5bd7f",
      "\"08afc072-b250-4964-b4a1-9828fbdc49a6.0\"",
      "e4b3540a-4468-4e0c-a1b8-bcf26246a4d5",
      "\"ff25911c-a6ca-41ed-a737-fcabb08705c5\"",
      "a7860fd0-0f77-4957-ad5a-13843f06d133",
      "\"589bbf35-9a04-4ba6-be7e-baded5ffaa95.0\"",
      "52a24be3-c3a6-4678-b74e-30db206f6bc7",
      "\"f04f36a4-a159-4f48-864c-57dc9797de9e\"",
      "3d2ea125-b8b5-4f54-a6ea-0c83ece62a71",
      "\"8e36319a-6c63-4eec-bd58-89903b38ee3a.0\"",
      "bb5ab9e0-6c28-44fc-a0a2-a84ac4008c0a",
      "\"8e36319a-6c63-4eec-bd58-89903b38ee3a.1\"",
      "f55020b9-82d5-4e7c-83e4-dd9cf70bd7dc",
      "\"666904cd-1393-47ee-bb74-e92933ba9953.1\"",
      "f70945f0-04ee-43a6-b202-9da1bb35ff1f",
      "\"666904cd-1393-47ee-bb74-e92933ba9953.0\"",
      "5274d46d-a7db-4b4b-b3b4-d8b81ce9a908",
      "\"05703b70-b486-43da-95b5-bfdf368a5a63\"",
      "d21af839-bede-442e-8e17-e7b4fd40343d",
      "\"2027368a-3c4e-40ee-8ffe-9b3a5ce1db1d\"",
      "a137bb19-1dfe-4b37-acec-c570f4a2d6bb",
      "\"263763f4-3618-4aba-8eb8-3d8c7b88a0ac\"",
      "c8eb959f-0903-409d-bcd0-f46ac49cbaa5",
      "\"d167a566-d94a-4c78-a836-07a955104a65\"",
      "3712be0c-45bb-40a7-8e21-0e7e39753bfa",
      "\"d167a566-d94a-4c78-a836-07a955104a65.1\"",
      "3a643271-be36-4f93-a417-d6d75eaff0c1",
      "\"d167a566-d94a-4c78-a836-07a955104a65.0\"",
      "bb2077c6-1fa3-462e-b234-cdf78d8c3fea",
      "\"3f9e1490-cb80-4a10-a41f-f0048da40932\"",
      "0c92bb6e-05cf-4b9d-9c6e-5e6ac5e3b18d",
      "\"03a64623-6235-44c8-880c-e8c901bb226a\"",
      "73dc7f96-8487-4db4-9047-2459278335a3",
      "\"995b3d9c-4f55-4678-b3ec-fdf6ac7867a4.0\"",
      "0fbb6700-043f-4c36-962b-034ef5bbdb50",
      "\"75f67c96-1345-48f7-a4c2-7a2090e07609.0\"",
      "17c4b582-c20f-4b15-b22c-5a3987c11f58",
      "\"4c7b8b06-8c32-468b-a1cc-abcdfb1fa32d\"",
      "a42d926b-a71a-4d31-86a5-5753414bc52f",
      "\"4048c6c0-83ed-4fe8-8f3e-6d5d78da84ee\"",
      "bcbcc91d-de2b-4403-8b3a-0e4400e389cf",
      "\"d9611a41-f8e2-4a26-aea2-b4c3e1306f0f\"",
      "2a7ebb59-c3f5-41b3-8535-ceeb508af4c7",
      "\"7ffbc900-1dd2-49a3-939a-03eec0531643\"",
      "9ccd043c-bc24-462a-a754-8f9fc6d26fba",
      "\"d584a457-788f-4938-ac1e-2b45dd57ad64.0\"",
      "c17f635d-e177-456d-b08e-a31400b5d463",
      "\"d584a457-788f-4938-ac1e-2b45dd57ad64.1\"",
      "3965656f-4a25-479e-94db-7d6e64542d98",
      "\"b25b832d-0af1-492d-b45d-03c81159b7ee.0\"",
      "0fa9fcd9-2403-42c0-ba27-0f9abbb88c22",
      "\"b25b832d-0af1-492d-b45d-03c81159b7ee.1\"",
      "9d9913af-69ce-41f9-bf21-40fdb695ec9c",
      "\"da9b6aa0-2526-4d6b-8b15-4c79a68f9d65\"",
      "bd24f59b-6374-4e4c-b40b-cb8dfeb9444b",
      "\"db1bf61f-f7fe-4fc3-afd4-9678aa480123\"",
      "628a2409-f392-4a55-bc1c-984de491f74e",
      "\"751aa565-9a8b-4724-8e75-0b21ec9814e2\"",
      "987d9064-078e-42e9-afa4-0a06122ca838",
      "\"53a502bd-6a6b-4c5b-956e-003b8e801e2f.0\"",
      "70a97703-472f-45d6-ba05-1ca134585d0f",
      "\"53a502bd-6a6b-4c5b-956e-003b8e801e2f.1\"",
      "827acfa3-59b3-4709-92d0-91f01d1c7bab",
      "\"0873f05d-28b1-4daa-8c4e-1c3f4056fc5f\"",
      "d5e16b98-ea8f-4c3a-985e-acd9c77345e0",
      "\"aa33592b-5766-44eb-9390-d0baaf638c65\"",
      "b4e5f70a-68e9-4652-aa1a-b0b96b1d1924",
      "\"f11eca8b-1d55-4f58-a6bc-f6cf182aea54\"",
      "e4c0239d-47f5-44a4-ac10-96e85b813ab3",
      "\"7ffbc900-1dd2-49a3-939a-03eec0531643.0\"",
      "c2663b82-47f2-427a-8447-e0dcebe1c102",
      "\"7ad8c639-3f48-40cc-b52c-3b2b19001bfb\"",
      "4c4e22c1-89d5-4202-97dc-43eddbcaadf8",
      "\"7ffbc900-1dd2-49a3-939a-03eec0531643.1\"",
      "835cff3e-8de9-4864-92b7-724b7309c84a",
      "\"3719bc5b-e30c-4e7b-8be2-d318942c1bbb\"",
      "ca09e586-f33b-4cce-9a4c-aa369c9a6cad",
      "\"ff25911c-a6ca-41ed-a737-fcabb08705c5.0\"",
      "94754d82-8dcf-4a69-b8a6-78fe50780940",
      "\"096b0151-2b27-4143-8847-0301a2a27e29.0\"",
      "98260f7c-0f58-4320-8008-7d736c38fb0e",
      "\"25b32bd5-5b43-45d7-a5b7-7e376fd5f9e6.0\"",
      "150bf029-411c-4a70-b1ba-3aebbcd026c8",
      "\"b93b8a00-1d30-40cd-acb1-39b2e99b4533\"",
      "7dfb5257-024f-4718-abed-693920471053",
      "\"f9e0d3d9-9c44-4977-b960-ad60e0f24ab4\"",
      "e4ace6ad-0089-4ea7-8ab4-c30b53040420",
      "\"3bf92c9e-3e25-46e6-8b12-3f71dbad87f2\"",
      "b5660332-b5a2-46df-aefa-5095a747661e",
      "\"be138a2d-1799-425c-a7c4-5ff8988e2078\"",
      "feddeff5-b202-4f9c-8d4f-9c3f9e881ac9",
      "\"2d3a55b6-d053-4523-819d-ea571b2d4d87.0\"",
      "66959895-dbbc-4a2b-9950-dfa1fe967cb8",
      "\"bf817365-eaf3-4ad3-b2dc-01e985a8a4f1\"",
      "5493bd88-299a-4263-9b2c-39299526de17",
      "\"7d74b708-51a3-4fd9-b0ef-c6bab91e50bf\"",
      "8c5c8fb5-85d8-4544-9956-59b76518eead",
      "\"540c8a44-8bc1-4cd9-ae46-dfe0b3e36d2d\"",
      "758ded0e-044c-4916-b41e-248e7d56c6cc",
      "\"d8bfb94e-0681-4e36-a481-568ab7beb833\"",
      "e73f6eae-82e8-41b1-8e6a-2cefd1813289",
      "\"19cadc2a-d840-492a-9e00-5103ff0c46e6\"",
      "2475f626-4138-4f2b-b690-26a1ce20583e",
      "\"0873f05d-28b1-4daa-8c4e-1c3f4056fc5f.0\"",
      "1c9e6a4d-8cf0-4988-ae64-1cb97e1a5354",
      "\"aa33592b-5766-44eb-9390-d0baaf638c65.0\"",
      "0c2fcdfe-0b86-426e-b751-6089bb0bc639",
      "\"aa33592b-5766-44eb-9390-d0baaf638c65.1\"",
      "8c728ab7-3f9d-49c9-a48f-de528893ac4e",
      "\"root\"",
      "3fca67a4-31ec-4507-a432-dba8de8a80c0",
      "\"203b0ebc-81de-40c3-806d-0fd1006d77aa.0\"",
      "d740ef86-8419-4373-96a8-cfde578938df",
      "\"84a67252-360d-4fdc-a457-8d9245cc3d1e\"",
      "54cf9017-baa5-4ae1-b03a-bcba62dcdf6e",
      "\"bea5b9bb-5d8a-48e1-8386-7c6209f8419a\"",
      "259191ac-9153-41c3-8fdb-85ba790749d9",
      "\"f04f36a4-a159-4f48-864c-57dc9797de9e.0\"",
      "11adb4a7-a0c1-4960-996b-1f62940a8a6f",
      "\"f04f36a4-a159-4f48-864c-57dc9797de9e.1\"",
      "dc3b929b-425b-404e-9b39-0f636de3b628",
      "\"04339751-f8c9-4b26-a6bf-1011e0ca0b38.0\"",
      "c233f60b-74a7-473a-997e-3853e5e61405",
      "\"8765d17e-58d7-48d2-a8e4-45503212585f\"",
      "2200fecc-2e9a-40af-adee-71db91a42463",
      "\"190c6ebb-4768-4dda-99fe-e0c6af309754\"",
      "a14cf9d8-aa1a-45e3-b636-318a64977969",
      "\"876f41c7-50e6-451a-9b0c-3e016a9bd568\"",
      "551f308e-6612-4f39-84bf-73c2987a1d53",
      "\"6e73ab11-6999-43d4-9f8a-2520528935e6.0\"",
      "beb7e466-6bce-462b-8625-4bf1066f1025",
      "\"53a502bd-6a6b-4c5b-956e-003b8e801e2f\"",
      "e3aedb12-6f82-4baa-9de6-31caafce378e",
      "\"f11eca8b-1d55-4f58-a6bc-f6cf182aea54.0\"",
      "e54f3f1a-956f-49c8-9385-55e12ae2936e",
      "\"f11eca8b-1d55-4f58-a6bc-f6cf182aea54.1\"",
      "95392fca-b2bb-45e4-a902-7aec0fa9c405",
      "\"b5bc486b-7a4d-42c4-8400-9f99b66aac13\"",
      "cdc06761-0143-4b8c-b7e4-93a187be7405",
      "\"0cf127c6-0fc7-4098-aa79-62a709046253.0\"",
      "8cb9fbde-7793-4859-beba-96d72bebe10b",
      "\"0cf127c6-0fc7-4098-aa79-62a709046253.1\"",
      "c2e419cf-97b8-4354-b9c9-e631199b8470",
      "\"3dfee4d6-3b58-407c-86f3-6bed2681d0aa\"",
      "07e4abe6-e0ee-4ad5-86a4-2e9f38cdce85",
      "\"21b94ae9-e1ee-440d-ae9c-6426c480cf9d.0\"",
      "15f66b55-2b25-47c9-8593-fa5ea36018e2",
      "\"30955796-38bc-421f-a539-3e8e85da0004\"",
      "e000eb6a-1235-43f8-a096-0d803ba7a997",
      "\"492e1b68-f64c-4e9d-8f6d-aae6f8a0eb07.1\"",
      "78ba183a-bf07-4259-a407-343458cff0c5",
      "\"492e1b68-f64c-4e9d-8f6d-aae6f8a0eb07.0\"",
      "8cbc0216-fe94-424f-b7ac-71fe7d5d6252",
      "\"1b476c28-0b19-43a2-ae92-3e6b4b253045\"",
      "d1a32a63-71d2-46aa-9883-9137627ae89d",
      "\"3120f6da-fa75-46eb-8369-ca95fa0c9119.0\"",
      "970b0078-2d43-4063-b9f9-cabdb888e20c",
      "\"3120f6da-fa75-46eb-8369-ca95fa0c9119.1\"",
      "4a71b192-cfdc-4b15-baf0-ce266921858c",
      "\"40c132a9-ca7f-455f-9f8e-6c77bde70248\"",
      "d3b1b315-263b-4cfe-a334-92aac13708e7",
      "\"eb19fcb5-fb41-4c3f-9c0c-e4240ccbd429\"",
      "0dc0df22-849d-4981-97fd-1734fe42e622",
      "\"b3f509f3-3709-454a-b60a-93bfda77625c\"",
      "8027bf27-d48c-458c-95a9-dbf8c970aaf8",
      "\"be138a2d-1799-425c-a7c4-5ff8988e2078.0\"",
      "77127c7e-746b-4e9c-a0bd-c2bcdfc4bb34",
      "\"ea1c4c07-31c9-468c-81f3-9c97f73ac98c.0\"",
      "8f214cfa-50b9-49f0-b45b-80efb2eaf046",
      "\"ea1c4c07-31c9-468c-81f3-9c97f73ac98c.1\"",
      "8386a6bd-97f8-4d4f-8c33-9e9fe00d85c9",
      "\"fb6e2a98-61ea-4b78-a59c-ebaf1386f77f.1\"",
      "3bdb066d-cc5c-4ea4-9997-18e2cae4fc36",
      "\"fb6e2a98-61ea-4b78-a59c-ebaf1386f77f.0\"",
      "72a41e1c-dfe7-414c-b0a6-11045a1555d5",
      "\"6e73ab11-6999-43d4-9f8a-2520528935e6\"",
      "fd223689-be35-4858-bb84-fe9ff2129ddd",
      "\"4b56dceb-1a14-4e0d-b55d-77ad106fe092.1\"",
      "f6b1bf26-b576-4b52-9cbf-20b4e3da6ea1",
      "\"4b56dceb-1a14-4e0d-b55d-77ad106fe092.0\"",
      "53bf40ea-814e-49af-a073-e3dba8261ddf",
      "\"618ecf4d-d381-4a2a-9509-8bdc53a7fabc\"",
      "636f749c-b44a-4565-b7a1-79acd7c4c53c",
      "\"3719bc5b-e30c-4e7b-8be2-d318942c1bbb.0\"",
      "60fdbbbd-75cc-4014-88a7-64f7b43923ec",
      "\"669157ff-6134-4936-ac9d-88d83514b1c9\"",
      "22c9f71b-9a9e-4d5f-88a7-2e265bc1e8f2",
      "\"3719bc5b-e30c-4e7b-8be2-d318942c1bbb.1\"",
      "27ae6c93-90eb-4e1a-8372-95d3f4a4054b",
      "\"7c36120b-ef3f-4c32-adf1-79e2298ecb99.0\"",
      "e9ba362c-4df4-42f9-b721-febc3180a127",
      "\"23cbde5c-e70d-4194-bf64-53779d7bc447.0\"",
      "c22b3b81-a44a-453e-97ad-9c81361a4f1f"
    ]
  ],
  "code_info_obj": [
    [
      "3",
      "1",
      "0",
      "\"\"",
      "0"
    ]
  ],
  "code_encoding_obj": "utf-8-sig"
}